nws_aurora/__init__.py
nws_aurora/cli.py
nws_aurora-0.0.6.dist-info/LICENSE
nws_aurora-0.0.6.dist-info/METADATA
nws_aurora-0.0.6.dist-info/WHEEL
nws_aurora-0.0.6.dist-info/entry_points.txt
nws_aurora-0.0.6.dist-info/top_level.txt
nws_aurora-0.0.6.dist-info/RECORD
