Metadata-Version: 2.1
Name: nws-aurora
Version: 0.0.6
Summary: Download forecast data for Aurora Borealis and Aurora Australis from the National Weather Service
Author-email: Ben Welsh <b@palewi.re>
License: MIT
Project-URL: Homepage, https://github.com/palewire/nws-aurora/
Project-URL: Issues, https://github.com/palewire/nws-aurora/issues
Classifier: Development Status :: 5 - Production/Stable
Classifier: Programming Language :: Python
Classifier: Programming Language :: Python :: 3
Classifier: Programming Language :: Python :: 3.9
Classifier: Programming Language :: Python :: 3.10
Classifier: Programming Language :: Python :: 3.11
Classifier: License :: OSI Approved :: MIT License
Requires-Python: >=3.9
License-File: LICENSE
Requires-Dist: pytz
Requires-Dist: bs4
Requires-Dist: requests
Requires-Dist: geojson
Requires-Dist: click
Requires-Dist: exceptiongroup ; python_version < "3.11"
